Metadata-Version: 2.1
Name: odoo10-addon-account-invoice-supplierinfo-update
Version: 10.0.1.0.2
Summary: In the supplier invoice, automatically updates all products whose unit price on the line is different from the supplier price
Home-page: https://github.com/OCA/account-invoicing
Author: Akretion,GRAP,Odoo Community Association (OCA)
Author-email: support@odoo-community.org
License: AGPL-3
Platform: UNKNOWN
Classifier: Programming Language :: Python
Classifier: Framework :: Odoo
Classifier: Framework :: Odoo :: 10.0
Classifier: License :: OSI Approved :: GNU Affero General Public License v3
Requires-Python: ~=2.7
Requires-Dist: odoo (<10.1dev,>=10.0)
